j2config/__init__.py
j2config/data_collect.py
j2config/func.py
j2config/general.py
j2config/j2.py
j2config/read_conditions.py
j2config/cmn/__init__.py
j2config/cmn/common_fn.py
j2config-0.1.1.dist-info/LICENSE
j2config-0.1.1.dist-info/METADATA
j2config-0.1.1.dist-info/WHEEL
j2config-0.1.1.dist-info/top_level.txt
j2config-0.1.1.dist-info/RECORD
