Metadata-Version: 2.1
Name: j2config
Version: 0.1.1
Summary: configuration generation using jinja2 - for Networking Geeks
Home-page: https://github.com/aliasgar1978/j2config
Author: ALIASGAR - ALI
Author-email: aholo2000@gmail.com
Classifier: Programming Language :: Python :: 3
Classifier: License :: OSI Approved :: MIT License
Classifier: Operating System :: OS Independent
Requires-Python: >=3.7
License-File: LICENSE
Requires-Dist: pandas
Requires-Dist: jinja2
Requires-Dist: xlrd
Requires-Dist: openpyxl
Requires-Dist: nettoolkit
Requires-Dist: nettoolkit-db
Requires-Dist: nettoolkit-common
